ibisml/__init__.py
ibisml/_version.py
ibisml/core.py
ibisml/select.py
ibisml/steps/__init__.py
ibisml/steps/common.py
ibisml/steps/encode.py
ibisml/steps/impute.py
ibisml/steps/standardize.py
ibisml/steps/temporal.py
ibisml/transforms/__init__.py
ibisml/transforms/common.py
ibisml/transforms/encode.py
ibisml/transforms/impute.py
ibisml/transforms/standardize.py
ibisml/transforms/temporal.py
ibisml-0.2.0.dist-info/LICENSE.txt
ibisml-0.2.0.dist-info/METADATA
ibisml-0.2.0.dist-info/WHEEL
ibisml-0.2.0.dist-info/top_level.txt
ibisml-0.2.0.dist-info/RECORD
