Metadata-Version: 2.1
Name: ibisml
Version: 0.2.0
Summary: Tools for developing ML pipelines using Ibis
License: Apache 2.0
Requires-Python: >=3.8
License-File: LICENSE.txt
Requires-Dist: ibis-framework
